ume/__init__.py
ume/ume.py
ume/utils.py
ume-0.1.1.dist-info/WHEEL
ume-0.1.1.dist-info/METADATA
ume-0.1.1.dist-info/RECORD
